mistral_pdf_to_markdown/__init__.py
mistral_pdf_to_markdown/main.py
mistral_pdf_to_markdown-1.2.0.dist-info/METADATA
mistral_pdf_to_markdown-1.2.0.dist-info/WHEEL
mistral_pdf_to_markdown-1.2.0.dist-info/entry_points.txt
mistral_pdf_to_markdown-1.2.0.dist-info/licenses/LICENSE
mistral_pdf_to_markdown-1.2.0.dist-info/RECORD
