Metadata-Version: 2.4
Name: mistral-pdf-to-markdown
Version: 1.2.0
Summary: A CLI tool to convert PDF files to Markdown using the Mistral AI OCR API.
License-File: LICENSE
Author: Arcangelo Massari
Author-email: info@arcangelomassari.com
Requires-Python: >=3.10,<4.0
Classifier: Programming Language :: Python :: 3
Classifier: Programming Language :: Python :: 3.10
Classifier: Programming Language :: Python :: 3.11
Classifier: Programming Language :: Python :: 3.12
Classifier: Programming Language :: Python :: 3.13
Classifier: Programming Language :: Python :: 3.14
Requires-Dist: click (>=8.1.8,<9.0.0)
Requires-Dist: mistralai (>=1.7.0,<2.0.0)
Requires-Dist: pypandoc (>=1.15,<2.0)
Requires-Dist: python-dotenv (>=1.1.0,<2.0.0)
Requires-Dist: weasyprint (>=66.0,<67.0)
